jefftadashi_utils/__init__.py
jefftadashi_utils/oui.py
jefftadashi_utils/rebuild_oui.py
jefftadashi_utils-0.0.7.dist-info/LICENSE
jefftadashi_utils-0.0.7.dist-info/METADATA
jefftadashi_utils-0.0.7.dist-info/WHEEL
jefftadashi_utils-0.0.7.dist-info/top_level.txt
jefftadashi_utils-0.0.7.dist-info/RECORD
