Metadata-Version: 2.1
Name: jefftadashi-utils
Version: 0.0.7
Summary: My general utilities Python module!
Home-page: https://github.com/JeffTadashi/jefftadashi_utils
Author: Jeff Tadashi Moy
Author-email: jeff@jefftadashi.com
License: gpl-3.0
Platform: UNKNOWN
Classifier: Programming Language :: Python :: 3
Classifier: Operating System :: OS Independent
Requires-Python: >=3.5
